[
  {
    "name": "764464_Praful",
    "count": 16,
    "respect_gain": 220.36,
    "respect_loss": 55.1
  },
  {
    "name": "ArchiAlert",
    "count": 11,
    "respect_gain": 149.24,
    "respect_loss": 37.32
  },
  {
    "name": "backa117",
    "count": 7,
    "respect_gain": 33.59,
    "respect_loss": 8.4
  },
  {
    "name": "BaldJonno",
    "count": 9,
    "respect_gain": 25.9,
    "respect_loss": 6.46
  },
  {
    "name": "Blazebugg",
    "count": 9,
    "respect_gain": 41.39,
    "respect_loss": 10.33
  },
  {
    "name": "Bobbelbo",
    "count": 16,
    "respect_gain": 173.1,
    "respect_loss": 43.32
  },
  {
    "name": "caits",
    "count": 6,
    "respect_gain": 24.36,
    "respect_loss": 6.09
  },
  {
    "name": "CaptainRinny",
    "count": 4,
    "respect_gain": 25.86,
    "respect_loss": 6.47
  },
  {
    "name": "Carljnz",
    "count": 8,
    "respect_gain": 105.4,
    "respect_loss": 26.36
  },
  {
    "name": "CJ120",
    "count": 11,
    "respect_gain": 72.18,
    "respect_loss": 18.04
  },
  {
    "name": "Ckreepa",
    "count": 14,
    "respect_gain": 182.48,
    "respect_loss": 45.62
  },
  {
    "name": "Daany56778",
    "count": 13,
    "respect_gain": 46.4,
    "respect_loss": 11.59
  },
  {
    "name": "datcracker420",
    "count": 8,
    "respect_gain": 68.03,
    "respect_loss": 17.02
  },
  {
    "name": "Delldax",
    "count": 2,
    "respect_gain": 25.74,
    "respect_loss": 6.44
  },
  {
    "name": "Deviyl",
    "count": 5,
    "respect_gain": 21.11,
    "respect_loss": 5.28
  },
  {
    "name": "Doomlegion",
    "count": 17,
    "respect_gain": 98.59,
    "respect_loss": 24.65
  },
  {
    "name": "err0r418125",
    "count": 17,
    "respect_gain": 83.97,
    "respect_loss": 20.99
  },
  {
    "name": "Fulgrim2",
    "count": 6,
    "respect_gain": 28.72,
    "respect_loss": 7.18
  },
  {
    "name": "HampyGampy",
    "count": 9,
    "respect_gain": 57.63,
    "respect_loss": 14.41
  },
  {
    "name": "Heisenberg2014",
    "count": 8,
    "respect_gain": 28.31,
    "respect_loss": 7.09
  },
  {
    "name": "hoppopotamus",
    "count": 4,
    "respect_gain": 19.32,
    "respect_loss": 4.84
  },
  {
    "name": "JaydusStrokka",
    "count": 18,
    "respect_gain": 89.1,
    "respect_loss": 22.28
  },
  {
    "name": "Jereos",
    "count": 3,
    "respect_gain": 12.57,
    "respect_loss": 3.15
  },
  {
    "name": "Kain_korso",
    "count": 6,
    "respect_gain": 41.51,
    "respect_loss": 10.39
  },
  {
    "name": "Kreachussy",
    "count": 12,
    "respect_gain": 33.52,
    "respect_loss": 8.39
  },
  {
    "name": "MrNoggins",
    "count": 12,
    "respect_gain": 118.7,
    "respect_loss": 29.64
  },
  {
    "name": "Onigirli_",
    "count": 10,
    "respect_gain": 41.76,
    "respect_loss": 10.46
  },
  {
    "name": "Postman_",
    "count": 7,
    "respect_gain": 47.71,
    "respect_loss": 11.93
  },
  {
    "name": "PowerMax",
    "count": 3,
    "respect_gain": 16.04,
    "respect_loss": 4.01
  },
  {
    "name": "SaintMichael",
    "count": 24,
    "respect_gain": 187.61,
    "respect_loss": 46.89
  },
  {
    "name": "SirJimboSliceSr",
    "count": 21,
    "respect_gain": 208.09,
    "respect_loss": 52.01
  },
  {
    "name": "Somehomelessmen",
    "count": 5,
    "respect_gain": 21.52,
    "respect_loss": 5.38
  },
  {
    "name": "Squith",
    "count": 8,
    "respect_gain": 37.93,
    "respect_loss": 9.47
  },
  {
    "name": "Wolfylein",
    "count": 11,
    "respect_gain": 43.6,
    "respect_loss": 10.9
  },
  {
    "name": "Xevi",
    "count": 18,
    "respect_gain": 103.8,
    "respect_loss": 25.95
  },
  {
    "name": "xKittehxKatx",
    "count": 8,
    "respect_gain": 33.99,
    "respect_loss": 8.51
  },
  {
    "name": "ZeTwilighTwizz",
    "count": 13,
    "respect_gain": 143.19,
    "respect_loss": 35.78
  },
  {
    "name": "Total",
    "count": 379,
    "respect_gain": 2712.32,
    "respect_loss": 678.14
  }
]