[
  {
    "name": "764464_Praful",
    "count": 2,
    "respect_gain": 4.24,
    "respect_loss": 1.06
  },
  {
    "name": "bitek",
    "count": 7,
    "respect_gain": 41.76,
    "respect_loss": 10.45
  },
  {
    "name": "Bobbelbo",
    "count": 2,
    "respect_gain": 4.95,
    "respect_loss": 1.23
  },
  {
    "name": "CaptainRinny",
    "count": 1,
    "respect_gain": 40,
    "respect_loss": 10
  },
  {
    "name": "Ckreepa",
    "count": 2,
    "respect_gain": 27.64,
    "respect_loss": 6.91
  },
  {
    "name": "datcracker420",
    "count": 5,
    "respect_gain": 49.21,
    "respect_loss": 12.31
  },
  {
    "name": "Deviyl",
    "count": 1,
    "respect_gain": 2.44,
    "respect_loss": 0.61
  },
  {
    "name": "G4B3",
    "count": 1,
    "respect_gain": 80,
    "respect_loss": 20
  },
  {
    "name": "Hershey54",
    "count": 1,
    "respect_gain": 2.24,
    "respect_loss": 0.56
  },
  {
    "name": "JaydusStrokka",
    "count": 1,
    "respect_gain": 4.38,
    "respect_loss": 1.1
  },
  {
    "name": "Kreachussy",
    "count": 1,
    "respect_gain": 6.29,
    "respect_loss": 1.57
  },
  {
    "name": "Mr_Lynch_Ryder",
    "count": 3,
    "respect_gain": 7.53,
    "respect_loss": 1.88
  },
  {
    "name": "MrNoggins",
    "count": 6,
    "respect_gain": 79.5,
    "respect_loss": 19.88
  },
  {
    "name": "nojura",
    "count": 2,
    "respect_gain": 5.65,
    "respect_loss": 1.41
  },
  {
    "name": "PeachesCat",
    "count": 1,
    "respect_gain": 4.25,
    "respect_loss": 1.06
  },
  {
    "name": "SirJimboSliceSr",
    "count": 5,
    "respect_gain": 14.33,
    "respect_loss": 3.59
  },
  {
    "name": "SPANJO22",
    "count": 2,
    "respect_gain": 6.36,
    "respect_loss": 1.59
  },
  {
    "name": "Wolfylein",
    "count": 1,
    "respect_gain": 3.78,
    "respect_loss": 0.94
  },
  {
    "name": "ZeTwilighTwizz",
    "count": 2,
    "respect_gain": 10.24,
    "respect_loss": 2.56
  },
  {
    "name": "Total",
    "count": 46,
    "respect_gain": 394.79,
    "respect_loss": 98.71
  }
]