{
  "1102071": {
    "name": "Ckreepa",
    "level": 75,
    "days_in_faction": 98
  },
  "1978647": {
    "name": "Delldax",
    "level": 89,
    "days_in_faction": 168
  },
  "2291615": {
    "name": "Daany56778",
    "level": 27,
    "days_in_faction": 172
  },
  "2594774": {
    "name": "MrShenanigans",
    "level": 65,
    "days_in_faction": 54
  },
  "2792892": {
    "name": "Xevi",
    "level": 56,
    "days_in_faction": 153
  },
  "2939779": {
    "name": "JaydusStrokka",
    "level": 59,
    "days_in_faction": 1054
  },
  "2967439": {
    "name": "VictoriaCicile",
    "level": 18,
    "days_in_faction": 77
  },
  "3150667": {
    "name": "CJ120",
    "level": 31,
    "days_in_faction": 111
  },
  "3157644": {
    "name": "SirJimboSliceSr",
    "level": 66,
    "days_in_faction": 180
  },
  "3163147": {
    "name": "bitek",
    "level": 59,
    "days_in_faction": 75
  },
  "3163171": {
    "name": "Kaleciatko",
    "level": 56,
    "days_in_faction": 75
  },
  "3171413": {
    "name": "xKittehxKatx",
    "level": 36,
    "days_in_faction": 179
  },
  "3251423": {
    "name": "Nuggets",
    "level": 60,
    "days_in_faction": 216
  },
  "3277325": {
    "name": "Kain_korso",
    "level": 59,
    "days_in_faction": 352
  },
  "3293671": {
    "name": "Carldica",
    "level": 69,
    "days_in_faction": 41
  },
  "3513090": {
    "name": "Squith",
    "level": 30,
    "days_in_faction": 150
  },
  "3562619": {
    "name": "Postman_",
    "level": 74,
    "days_in_faction": 438
  },
  "3563386": {
    "name": "Doomlegion",
    "level": 54,
    "days_in_faction": 416
  },
  "3599627": {
    "name": "CaptainRinny",
    "level": 60,
    "days_in_faction": 401
  },
  "3627681": {
    "name": "ZeTwilighTwizz",
    "level": 42,
    "days_in_faction": 378
  },
  "3722358": {
    "name": "Deviyl",
    "level": 25,
    "days_in_faction": 149
  },
  "3727751": {
    "name": "Bobbelbo",
    "level": 42,
    "days_in_faction": 240
  },
  "3774090": {
    "name": "Jereos",
    "level": 47,
    "days_in_faction": 263
  },
  "3793607": {
    "name": "MADSCOTBASTARD",
    "level": 45,
    "days_in_faction": 41
  },
  "3796175": {
    "name": "PowerMax",
    "level": 42,
    "days_in_faction": 190
  },
  "3844859": {
    "name": "Mr_Lynch_Ryder",
    "level": 25,
    "days_in_faction": 77
  },
  "3913421": {
    "name": "Wolfylein",
    "level": 47,
    "days_in_faction": 174
  },
  "3993903": {
    "name": "PeachesCat",
    "level": 28,
    "days_in_faction": 76
  },
  "2154856": {
    "name": "HowieAP",
    "level": 24,
    "days_in_faction": 35
  },
  "4123983": {
    "name": "LuoZane",
    "level": 17,
    "days_in_faction": 32
  },
  "2741991": {
    "name": "MrNoggins",
    "level": 100,
    "days_in_faction": 427
  },
  "4074605": {
    "name": "PrimoMontana",
    "level": 17,
    "days_in_faction": 24
  },
  "4170803": {
    "name": "_Davox_",
    "level": 12,
    "days_in_faction": 21
  },
  "3919065": {
    "name": "meirs",
    "level": 16,
    "days_in_faction": 21
  },
  "4165570": {
    "name": "Khan-drogo",
    "level": 13,
    "days_in_faction": 21
  },
  "4178800": {
    "name": "Kacmen4",
    "level": 7,
    "days_in_faction": 14
  },
  "4187169": {
    "name": "bogyesz",
    "level": 7,
    "days_in_faction": 13
  },
  "3551195": {
    "name": "ArchiAlert",
    "level": 64,
    "days_in_faction": 361
  },
  "4191720": {
    "name": "UhtredRagnar",
    "level": 13,
    "days_in_faction": 13
  },
  "4006094": {
    "name": "MissYachtBroker",
    "level": 26,
    "days_in_faction": 13
  },
  "4054180": {
    "name": "Rey_Juuzou-_-",
    "level": 23,
    "days_in_faction": 11
  },
  "4191394": {
    "name": "Shroar",
    "level": 11,
    "days_in_faction": 7
  },
  "4196596": {
    "name": "DaRuckus",
    "level": 14,
    "days_in_faction": 5
  },
  "4061600": {
    "name": "Trevor78",
    "level": 17,
    "days_in_faction": 25
  },
  "4221216": {
    "name": "Ctrlaltdelete_",
    "level": 6,
    "days_in_faction": 1
  }
}